{
  "source_pdf": "D:\\PW - IBPS SO Prelims Batch + Test series (Video course)\\New folder\\English dpp\\Floor Puzzle  Chapter wise DPP (English).pdf",
  "pages": [
    {
      "page_number": 1,
      "used_ocr": false,
      "text": "Reasoning\nQ1\nStudy the following information carefully and\nanswer the questions accordingly.\n \nNine people A, B, C, D, E, F, G, H and I live in a\nnine storey building, but not necessarily in the\nsame order. The lowermost floor is numbered 1\nand topmost floor is numbered 9. There are only\ntwo floors between B and H who live on the sixth\nfloor. I live just below B’s floor. There is a gap of\nfour floors between I and F. The number of floors\nbetween F and H is the same as the number of\nfloors between I and G. There are only two floors\nbetween G and A. E lives above D, but below C. D\ndoes not live on the lowest floor.\n \nFour of the following five are alike in a certain\nway based on their positions in the above\narrangement and so form a group. Which of the\nfollowing does not belong to the group?\n(A) I\n(B) E\n(C) H\n(D) C\n(E) A\nQ2\nStudy the following information carefully and\nanswer the questions accordingly.\n \nNine people A, B, C, D, E, F, G, H and I live in a\nnine storey building, but not necessarily in the\nsame order. The lowermost floor is numbered 1\nand topmost floor is numbered 9. There are only\ntwo floors between B and H who live on the sixth\nfloor. I live just below B’s floor. There is a gap of\nfour floors between I and F. The number of floors\nbetween F and H is the same as the number of\nfloors between I and G. There are only two floors\nbetween G and A. E lives above D, but below C. D\ndoes not live on the lowest floor.\n \nHow many floors are there between D and E?\n(A) Two\n(B) Three\n(C) None\n(D) Four\n(E) Five\nQ3\nStudy the following information carefully and\nanswer the questions accordingly.\n \nNine people A, B, C, D, E, F, G, H and I live in a\nnine storey building, but not necessarily in the\nsame order. The lowermost floor is numbered 1\nand topmost floor is numbered 9. There are only\ntwo floors between B and H who live on the sixth\nfloor. I live just below B’s floor. There is a gap of\nfour floors between I and F. The number of floors\nbetween F and H is the same as the number of\nfloors between I and G. There are only two floors\nbetween G and A. E lives above D, but below C. D\ndoes not live on the lowest floor.\n \nWhich of the following statements is/are true?\n(A) G lives on fourth floor\n(B) Three people lives between H and C\n(C) D lives just below H\n(D) No one live above B\n(E) All are true\nQ4\nStudy the following information carefully and\nanswer the questions accordingly.\n \nNine people A, B, C, D, E, F, G, H and I live in a\nnine storey building, but not necessarily in the\nsame order. The lowermost floor is numbered 1\nand topmost floor is numbered 9. There are only\ntwo floors between B and H who live on the sixth\nfloor. I live just below B’s floor. There is a gap of\nfour floors between I and F. The number of floors\n \nFloor Puzzle",
      "tables": [],
      "images": []
    },
    {
      "page_number": 2,
      "used_ocr": false,
      "text": "between F and H is the same as the number of\nfloors between I and G. There are only two floors\nbetween G and A. E lives above D, but below C. D\ndoes not live on the lowest floor.\n \nWho among the following lives on the ninth floor\n?\n(A) G\n(B) D\n(C) F\n(D) C\n(E) B\nQ5\nDirections: Study the following data carefully\nand answer the questions accordingly.\nNine people(J,K,L,M,N,O,P,Q and R) are living in\nan eight storey building. There are eight floors\nabove the ground floor(G). The topmost floor is 8\nand the lowermost floor is G. Two people live\nbetween O and N. Three people live between P\nand L. J lives on an odd number floor below floor\n7. Two people live between J and M. M doesn’t\nlive on the ground floor. Three people live\nbetween K and N. K lives above N. P lives below\nK but above O. Two people live between R and Q.\nQ lives below N but above O. R neither lives\nabove J nor M. L lives below J.\nFind the odd one out?\n(A) M\n(B) R\n(C) L\n(D) P\n(E) K\nQ6\nDirections: Study the following data carefully\nand answer the questions accordingly.\nNine people(J,K,L,M,N,O,P,Q and R) are living in\nan eight storey building. There are eight floors\nabove the ground floor(G). The topmost floor is 8\nand the lowermost floor is G. Two people live\nbetween O and N. Three people live between P\nand L. J lives on an odd number floor below floor\n7. Two people live between J and M. M doesn’t\nlive on the ground floor. Three people live\nbetween K and N. K lives above N. P lives below\nK but above O. Two people live between R and Q.\nQ lives below N but above O. R neither lives\nabove J nor M. L lives below J.\nHow many floors are there between K’s floor\nand Q’s floor?\n(A) 4\n(B) 5\n(C) 6\n(D) 7\n(E) 3\nQ7\nDirections: Study the following data carefully\nand answer the questions accordingly.\nNine people(J,K,L,M,N,O,P,Q and R) are living in\nan eight storey building. There are eight floors\nabove the ground floor(G). The topmost floor is 8\nand the lowermost floor is G. Two people live\nbetween O and N. Three people live between P\nand L. J lives on an odd number floor below floor\n7. Two people live between J and M. M doesn’t\nlive on the ground floor. Three people live\nbetween K and N. K lives above N. P lives below\nK but above O. Two people live between R and Q.\nQ lives below N but above O. R neither lives\nabove J nor M. L lives below J.\nWho lives immediately above P?\n(A) M\n(B) L\n(C) O\n(D) K\n(E) P\nQ8\nDirections: Study the following data carefully\nand answer the questions accordingly.\nNine people(J,K,L,M,N,O,P,Q and R) are living in\nan eight storey building. There are eight floors\nabove the ground floor(G). The topmost floor is 8\nand the lowermost floor is G. Two people live\nbetween O and N. Three people live between P\nand L. J lives on an odd number floor below floor\n7. Two people live between J and M. M doesn’t\nlive on the ground floor. Three people live\nbetween K and N. K lives above N. P lives below\nK but above O. Two people live between R and Q.\nQ lives below N but above O. R neither lives\nabove J nor M. L lives below J.\nWho lives on floor 4?\n(A) K\n(B) J\n(C) N\n(D) Q\n(E) R\nQ9",
      "tables": [],
      "images": []
    },
    {
      "page_number": 3,
      "used_ocr": false,
      "text": "Directions: Study the following data carefully\nand answer the questions accordingly.\nNine people(J,K,L,M,N,O,P,Q and R) are living in\nan eight storey building. There are eight floors\nabove the ground floor(G). The topmost floor is 8\nand the lowermost floor is G. Two people live\nbetween O and N. Three people live between P\nand L. J lives on an odd number floor below floor\n7. Two people live between J and M. M doesn’t\nlive on the ground floor. Three people live\nbetween K and N. K lives above N. P lives below\nK but above O. Two people live between R and Q.\nQ lives below N but above O. R neither lives\nabove J nor M. L lives below J.\nWho lives on the third floor from the bottom?\n(A) P\n(B) K\n(C) L\n(D) O\n(E) N\nQ10\nDirections: Study the following data carefully\nand answer the questions accordingly.\nNine people(J,K,L,M,N,O,P,Q and R) live in a nine\nstorey building. The topmost floor is 9 and the\nlowermost floor is 1. Two people live between N\nand R. Two people live between R and M. M\nneither lives on the topmost floor nor on the\nlowermost floor. O lives on the fifth floor. Two\npeople live between O and Q. Two people live\nbetween J and L. L does not live on the topmost\nfloor. N lives above M. M doesn’t live below P.\nThree people live between Q and J. K lives above\nL.\nWho lives immediately above K?\n(A) J\n(B) L\n(C) M\n(D) Q\n(E) N\nQ11\nDirections: Study the following data carefully\nand answer the questions accordingly.\nNine people(S,T,U,V,W,X,Y,Z and A) live in a nine\nstorey building. The topmost floor is 9 and the\nbottommost floor is 1. A lives three floors above\nT. Two people live between T and Z. T lives above\nZ. S lives on floor number 6. Two people live\nbetween S and X. X lives above W. T doesn’t live\nimmediately below S. Two people live between V\nand Y. A lives below V. U lives below W.\nWho lives immediately below X?\n(A) A\n(B) T\n(C) W\n(D) V\n(E) Y\nQ12\nRead the information given below carefully and\nanswer the questions accordingly.\nEight persons - A, G, J, M, P, R, V, and Y are living\non different floors in the same building having\neight floors. The bottom floor is numbered 1, the\nfloor above it is numbered 2 and so on.\nFour persons are living between M and V. M is\nliving above V. V is living immediately above R. A\nneither lives on an odd-numbered floor nor on\ntop most floor. Three persons are living between\nP and R. Y lives below R. One person lives\nbetween V and G.\n \nHow many persons live between R and M?\n(A) 4\n(B) 3\n(C) 6\n(D) 5\n(E) 2\nQ13\nRead the information given below carefully and\nanswer the questions accordingly.\nEight persons - A, G, J, M, P, R, V, and Y are living\non different floors in the same building having\neight floors. The bottom floor is numbered 1, the\nfloor above it is numbered 2 and so on.Four\npersons are living between M and V. M is living\nabove V. V is living immediately above R. A\nneither lives on an odd-numbered floor nor on\ntop most floor. Three persons are living between\nP and R. Y lives below R. One person lives\nbetween V and G.\n \nWhich of the following combination is true\naccording to the given arrangement?\n(A) 3rd floor - Y\n(B) 2nd floor - V\n(C) 7th floor - J",
      "tables": [],
      "images": []
    },
    {
      "page_number": 4,
      "used_ocr": false,
      "text": "(D) 8th floor - G\n(E) 1st floor - M\nQ14\nRead the information given below carefully and\nanswer the questions accordingly.\nEight persons - A, G, J, M, P, R, V, and Y are living\non different floors in the same building having\neight floors. The bottom floor is numbered 1, the\nfloor above it is numbered 2 and so on.Four\npersons are living between M and V. M is living\nabove V. V is living immediately above R. A\nneither lives on an odd-numbered floor nor on\ntop most floor. Three persons are living between\nP and R. Y lives below R. One person lives\nbetween V and G.\n \nWhich of the following pair is living on bottom\nfloor and top floor respectively?\n(A) Y - V\n(B) Y - M\n(C) A - P\n(D) G - M\n(E) A - R\nQ15\nRead the information given below carefully and\nanswer the questions accordingly.\nEight persons - A, G, J, M, P, R, V, and Y are living\non different floors in the same building having\neight floors. The bottom floor is numbered 1, the\nfloor above it is numbered 2 and so on.Four\npersons are living between M and V. M is living\nabove V. V is living immediately above R. A\nneither lives on an odd-numbered floor nor on\ntop most floor. Three persons are living between\nP and R. Y lives below R. One person lives\nbetween V and G.\n \nWho among the following is living on 5th floor?\n(A) Y\n(B) V\n(C) J\n(D) G\n(E) R\nQ16\nRead the information given below carefully and\nanswer the questions accordingly.\nEight persons - A, G, J, M, P, R, V, and Y are living\non different floors in the same building having\neight floors. The bottom floor is numbered 1, the\nfloor above it is numbered 2 and so on.Four\npersons are living between M and V. M is living\nabove V. V is living immediately above R. A\nneither lives on an odd-numbered floor nor on\ntop most floor. Three persons are living between\nP and R. Y lives below R. One person lives\nbetween V and G.\n \nWho is living on the floor just above P?\n(A) Y\n(B) V\n(C) J\n(D) G\n(E) P\nQ17\nRead the information given below carefully and\nanswer the questions accordingly.\n \nTen persons I, J, K, L, M, N, O, P, Q, and R are\nliving in 10-storey building but not necessarily in\nthe same order.\nM is living on an even-numbered floor above the\nfloor number 6. Three persons are living between\nthe floors on which M and P are living. Only four\npersons are living between the floors on which P\nand O are living. K is living immediately above\nthe floor on which O is living. Q is living on the\nfloor number 3. There is only one floor between\nthe floor on which P is living and the floor on\nwhich J is living. J is living above P. L is living\nimmediately above Q. N is living above I but\nbelow J.\n \nFind the odd one out from the following?\n(A) R\n(B) N\n(C) L\n(D) I\n(E) O\nQ18\nRead the information given below carefully and\nanswer the questions accordingly.\nTen persons I, J, K, L, M, N, O, P, Q, and R are\nliving in 10-storey building but not necessarily in\nthe same order.\nM is living on an even-numbered floor above the\nfloor number 6. Three persons are living between",
      "tables": [],
      "images": []
    },
    {
      "page_number": 5,
      "used_ocr": false,
      "text": "the floors on which M and P are living. Only four\npersons are living between the floors on which P\nand O are living. K is living immediately above\nthe floor on which O is living. Q is living on the\nfloor number 3. There is only one floor between\nthe floor on which P is living and the floor on\nwhich J is living. J is living above P. L is living\nimmediately above Q. N is living above I but\nbelow J.\nOn which of the following floors does J live?\n(A) 4\n(B) 8\n(C) 6\n(D) 2\n(E) 10\nQ19\nRead the information given below carefully and\nanswer the questions accordingly.\n \nTen persons I, J, K, L, M, N, O, P, Q, and R are\nliving in 10-storey building but necessarily in the\nsame order.\nM is living on an even-numbered floor above the\nfloor number 6. Three persons are living between\nthe floors on which M and P are living. Only four\npersons are living between the floors on which P\nand O are living. K is living immediately above\nthe floor on which O is living. Q is living on the\nfloor number 3. There is only one floor between\nthe floor on which P is living and the floor on\nwhich J is living. J is living above P. L is living\nimmediately above Q. N is living above I but\nbelow J.\n \nWhich among the following pair is living on top\nfloor and bottom floor?\n(A) M - O\n(B) K - J\n(C) N - L\n(D) I - Q\n(E) None of these\nQ20\nRead the information given below carefully and\nanswer the questions accordingly.\nTen persons I, J, K, L, M, N, O, P, Q, and R are\nliving in 10-storey building but not necessarily in\nthe same order.\nM is living on an even-numbered floor above the\nfloor number 6. Three persons are living between\nthe floors on which M and P are living. Only four\npersons are living between the floors on which P\nand O are living. K is living immediately above\nthe floor on which O is living. Q is living on the\nfloor number 3. There is only one floor between\nthe floor on which P is living and the floor on\nwhich J is living. J is living above P. L is living\nimmediately above Q. N is living above I but\nbelow J.\nWho among the following is living on floor 7?\n(A) R\n(B) K\n(C) N\n(D) I\n(E) M\nQ21\nRead the information given below carefully and\nanswer the questions accordingly.\n \nTen persons I, J, K, L, M, N, O, P, Q, and R are\nliving in 10-storey building but necessarily in the\nsame order.\nM is living on an even-numbered floor above the\nfloor number 6. Three persons are living between\nthe floors on which M and P are living. Only four\npersons are living between the floors on which P\nand O are living. K is living immediately above\nthe floor on which O is living. Q is living on the\nfloor number 3. There is only one floor between\nthe floor on which P is living and the floor on\nwhich J is living. J is living above P. L is living\nimmediately above Q. N is living above I but\nbelow J.\n \nWho among the following is living on three floors\nabove floor 2?\n(A) R\n(B) K\n(C) N\n(D) I\n(E) None of these\nQ22\nDirections: Study the following data carefully\nand answer accordingly.",
      "tables": [],
      "images": []
    },
    {
      "page_number": 6,
      "used_ocr": false,
      "text": "Eight people live in an eight-story building. One\nperson lives on one floor. The ground floor is\nnumbered 1 and the top floor is numbered 8. L\nlives below Y and above Q but not immediately. L\ndoes not live on the fourth floor. Q lives on an\neven numbered floor. People lives between S and\nQ are more or less than two. X lives immediately\nabove O, who lives below V. Three people live\nbetween S and U. Two people live between U,\nwho lives above the fourth floor and Y.\nFind the correct combination.\n(A) V- 6th floor\n(B) S – 2nd floor\n(C) Q – 3rd floor\n(D) X – 4th floor\n(E) None is correct\nQ23\nDirections: Study the following data carefully\nand answer accordingly.\nEight people live in an eight-story building. One\nperson lives on one floor. The ground floor is\nnumbered 1 and the top floor is numbered 8. L\nlives below Y and above Q but not immediately. L\ndoes not live on the fourth floor. Q lives on an\neven numbered floor. People lives between S and\nQ are more or less than two. X lives immediately\nabove O, who lives below V. Three people live\nbetween S and U. Two people live between U,\nwho lives above the fourth floor and Y.\nFind the odd one.\n(A) V\n(B) S\n(C) O\n(D) U\n(E) L\nQ24\nDirections: Study the following data carefully\nand answer accordingly.\nEight people live in an eight-story building. One\nperson lives on one floor. The ground floor is\nnumbered 1 and the top floor is numbered 8. L\nlives below Y and above Q but not immediately. L\ndoes not live on the fourth floor. Q lives on an\neven numbered floor. People lives between S and\nQ are more or less than two. X lives immediately\nabove O, who lives below V. Three people live\nbetween S and U. Two people live between U,\nwho lives above the fourth floor and Y.\nHow many people live between V and U?\n(A) Six\n(B) Five\n(C) One\n(D) Three\n(E) None of these\nQ25\nDirections: Study the following data carefully\nand answer accordingly.\nEight people live in an eight-story building. One\nperson lives on one floor. The ground floor is\nnumbered 1 and the top floor is numbered 8. L\nlives below Y and above Q but not immediately. L\ndoes not live on the fourth floor. Q lives on an\neven numbered floor. People lives between S and\nQ are more or less than two. X lives immediately\nabove O, who lives below V. Three people live\nbetween S and U. Two people live between U,\nwho lives above the fourth floor and Y.\nWho among the following lives between Q and\nX?\n(A) S\n(B) L\n(C) U\n(D) O\n(E) None of these\nQ26\nDirections: Study the following data carefully\nand answer accordingly.\nEight people live in an eight-story building. One\nperson lives on one floor. The ground floor is\nnumbered 1 and the top floor is numbered 8. L\nlives below Y and above Q but not immediately. L\ndoes not live on the fourth floor. Q lives on an\neven numbered floor. People lives between S and\nQ are more or less than two. X lives immediately\nabove O, who lives below V. Three people live\nbetween S and U. Two people live between U,\nwho lives above the fourth floor and Y.\nWho lives on the top floor?\n(A) V\n(B) S\n(C) Y\n(D) O\n(E) None of these\nQ27\nDirections: Study the following data carefully\nand answer accordingly.",
      "tables": [],
      "images": []
    },
    {
      "page_number": 7,
      "used_ocr": false,
      "text": "Eight persons M, N, O, P, Q, R, S and T live on\ndifferent \nfloors \nof \na \nbuilding \nsuch \nthat\nbottommost floor is numbered as 1, floor above it\nas 2 and so on.\nO lives above R’s floor but not on the topmost\nfloor. P lives just above M and on the even\nnumbered floor. S lives two floors above N, who\nlives on odd numbered floor. T lives on\nbottommost floor. P doesn’t live on the topmost\nfloor.\nHow many persons live between S’s and R’s\nfloor?\n(A) Two\n(B) Four\n(C) Three\n(D) One\n(E) Five\nQ28\nDirections: Study the following data carefully\nand answer accordingly.\nEight persons M, N, O, P, Q, R, S and T live on\ndifferent \nfloors \nof \na \nbuilding \nsuch \nthat\nbottommost floor is numbered as 1, floor above it\nas 2 and so on.\nO lives above R’s floor but not on the topmost\nfloor. P lives just above M and on the even\nnumbered floor. S lives two floors above N, who\nlives on odd numbered floor. T lives on\nbottommost floor. P doesn’t live on the topmost\nfloor.\nWho among the following lives on topmost floor?\n(A) O\n(B) S\n(C) Q\n(D) M\n(E) R\nQ29\nDirections: Study the following data carefully\nand answer accordingly.\nEight persons M, N, O, P, Q, R, S and T live on\ndifferent \nfloors \nof \na \nbuilding \nsuch \nthat\nbottommost floor is numbered as 1, floor above it\nas 2 and so on.\nO lives above R’s floor but not on the topmost\nfloor. P lives just above M and on the even\nnumbered floor. S lives two floors above N, who\nlives on odd numbered floor. T lives on\nbottommost floor. P doesn’t live on the topmost\nfloor.\n____ lives just below R’s floor.\n(A) M\n(B) P\n(C) Q\n(D) S\n(E) T",
      "tables": [],
      "images": []
    },
    {
      "page_number": 8,
      "used_ocr": false,
      "text": "Answer Key\nQ1 \n(D)\nQ2 \n(A)\nQ3 \n(C)\nQ4 \n(D)\nQ5 \n(E)\nQ6 \n(B)\nQ7 \n(D)\nQ8 \n(E)\nQ9 \n(C)\nQ10 (D)\nQ11 \n(D)\nQ12 (D)\nQ13 (C)\nQ14 (B)\nQ15 (D)\nQ16 (C)\nQ17 \n(C)\nQ18 (B)\nQ19 (A)\nQ20 (C)\nQ21 (D)\nQ22 (D)\nQ23 (E)\nQ24 (C)\nQ25 (D)\nQ26 (C)\nQ27 (B)\nQ28 (C)\nQ29 (E)",
      "tables": [],
      "images": []
    },
    {
      "page_number": 9,
      "used_ocr": false,
      "text": "Hints & Solutions\nQ1\nText Solution:\nThere are only two floors between B and H who\nlive on the sixth floor.\nI live just below B’s floor.\nThere is a gap of four floors between I and F.\nThe number of floors between F and H is the\nsame as the number of floors between I and G.\nThere are only two floors between G and A.",
      "tables": [],
      "images": [
        "output\\images\\floor_puzzle_chapter_wise_dpp_english\\floor_puzzle_chapter_wise_dpp_english_p009_img01.png",
        "output\\images\\floor_puzzle_chapter_wise_dpp_english\\floor_puzzle_chapter_wise_dpp_english_p009_img02.png",
        "output\\images\\floor_puzzle_chapter_wise_dpp_english\\floor_puzzle_chapter_wise_dpp_english_p009_img03.png",
        "output\\images\\floor_puzzle_chapter_wise_dpp_english\\floor_puzzle_chapter_wise_dpp_english_p009_img04.png"
      ]
    },
    {
      "page_number": 10,
      "used_ocr": false,
      "text": "E lives above D, but below C.\nD does not live on the lowest floor.\nCase 1: is eliminated.\nQ2\nText Solution:\nThere are only two floors between B and H, who\nlive on the sixth floor.\nI live just below B’s floor.",
      "tables": [],
      "images": [
        "output\\images\\floor_puzzle_chapter_wise_dpp_english\\floor_puzzle_chapter_wise_dpp_english_p010_img01.png",
        "output\\images\\floor_puzzle_chapter_wise_dpp_english\\floor_puzzle_chapter_wise_dpp_english_p010_img02.png",
        "output\\images\\floor_puzzle_chapter_wise_dpp_english\\floor_puzzle_chapter_wise_dpp_english_p010_img03.png",
        "output\\images\\floor_puzzle_chapter_wise_dpp_english\\floor_puzzle_chapter_wise_dpp_english_p010_img04.png"
      ]
    },
    {
      "page_number": 11,
      "used_ocr": false,
      "text": "There is a gap of four floors between I and F.\nThe number of floors between F and H is the\nsame as the number of floors between I and G.\nThere are only two floors between G and A.\nE lives above D, but below C.",
      "tables": [],
      "images": [
        "output\\images\\floor_puzzle_chapter_wise_dpp_english\\floor_puzzle_chapter_wise_dpp_english_p011_img01.png",
        "output\\images\\floor_puzzle_chapter_wise_dpp_english\\floor_puzzle_chapter_wise_dpp_english_p011_img02.png",
        "output\\images\\floor_puzzle_chapter_wise_dpp_english\\floor_puzzle_chapter_wise_dpp_english_p011_img03.png",
        "output\\images\\floor_puzzle_chapter_wise_dpp_english\\floor_puzzle_chapter_wise_dpp_english_p011_img04.png"
      ]
    },
    {
      "page_number": 12,
      "used_ocr": false,
      "text": "D does not live on the lowest floor.\nCase 1: is eliminated.\nQ3\nText Solution:\nThere are only two floors between B and H, who\nlive on the sixth floor.\nI live just below B’s floor.\nThere is a gap of four floors between I and F.",
      "tables": [],
      "images": [
        "output\\images\\floor_puzzle_chapter_wise_dpp_english\\floor_puzzle_chapter_wise_dpp_english_p012_img01.png",
        "output\\images\\floor_puzzle_chapter_wise_dpp_english\\floor_puzzle_chapter_wise_dpp_english_p012_img02.png",
        "output\\images\\floor_puzzle_chapter_wise_dpp_english\\floor_puzzle_chapter_wise_dpp_english_p012_img03.png",
        "output\\images\\floor_puzzle_chapter_wise_dpp_english\\floor_puzzle_chapter_wise_dpp_english_p012_img04.png"
      ]
    },
    {
      "page_number": 13,
      "used_ocr": false,
      "text": "The number of floors between F and H is the\nsame as the number of floors between I and G.\nThere are only two floors between G and A.\nE lives above D, but below C.\nD does not live on the lowest floor.",
      "tables": [],
      "images": [
        "output\\images\\floor_puzzle_chapter_wise_dpp_english\\floor_puzzle_chapter_wise_dpp_english_p013_img01.png",
        "output\\images\\floor_puzzle_chapter_wise_dpp_english\\floor_puzzle_chapter_wise_dpp_english_p013_img02.png",
        "output\\images\\floor_puzzle_chapter_wise_dpp_english\\floor_puzzle_chapter_wise_dpp_english_p013_img03.png",
        "output\\images\\floor_puzzle_chapter_wise_dpp_english\\floor_puzzle_chapter_wise_dpp_english_p013_img04.png"
      ]
    },
    {
      "page_number": 14,
      "used_ocr": false,
      "text": "Case 1: is eliminated.\nQ4\nText Solution:\nThere are only two floors between B and H, who\nlive on the sixth floor.\nI live just below B’s floor.\nThere is a gap of four floors between I and F.\nThe number of floors between F and H is the\nsame as the number of floors between I and G.",
      "tables": [],
      "images": [
        "output\\images\\floor_puzzle_chapter_wise_dpp_english\\floor_puzzle_chapter_wise_dpp_english_p014_img01.png",
        "output\\images\\floor_puzzle_chapter_wise_dpp_english\\floor_puzzle_chapter_wise_dpp_english_p014_img02.png",
        "output\\images\\floor_puzzle_chapter_wise_dpp_english\\floor_puzzle_chapter_wise_dpp_english_p014_img03.png",
        "output\\images\\floor_puzzle_chapter_wise_dpp_english\\floor_puzzle_chapter_wise_dpp_english_p014_img04.png"
      ]
    },
    {
      "page_number": 15,
      "used_ocr": false,
      "text": "There are only two floors between G and A.\nE lives above D, but below C.\nD does not live on the lowest floor.\nCase 1: is eliminated.\nQ5\nText Solution:\n1. J lives on an odd number floor below floor 7.\n2. Two people live between J and M.\n3. M doesn’t live on the ground floor.\nCASE 1",
      "tables": [],
      "images": [
        "output\\images\\floor_puzzle_chapter_wise_dpp_english\\floor_puzzle_chapter_wise_dpp_english_p015_img01.png",
        "output\\images\\floor_puzzle_chapter_wise_dpp_english\\floor_puzzle_chapter_wise_dpp_english_p015_img02.png",
        "output\\images\\floor_puzzle_chapter_wise_dpp_english\\floor_puzzle_chapter_wise_dpp_english_p015_img03.png",
        "output\\images\\floor_puzzle_chapter_wise_dpp_english\\floor_puzzle_chapter_wise_dpp_english_p015_img04.png"
      ]
    },
    {
      "page_number": 16,
      "used_ocr": false,
      "text": "CASE 2\nCASE 3\nCASE 4\n4. Three people live between K and N.\n5. K lives above N.\n6. Two people live between O and N.\n7. Q lives below N but above O.\nCASE 1\nCASE 2 (a)",
      "tables": [],
      "images": [
        "output\\images\\floor_puzzle_chapter_wise_dpp_english\\floor_puzzle_chapter_wise_dpp_english_p016_img01.png",
        "output\\images\\floor_puzzle_chapter_wise_dpp_english\\floor_puzzle_chapter_wise_dpp_english_p016_img02.png",
        "output\\images\\floor_puzzle_chapter_wise_dpp_english\\floor_puzzle_chapter_wise_dpp_english_p016_img03.png",
        "output\\images\\floor_puzzle_chapter_wise_dpp_english\\floor_puzzle_chapter_wise_dpp_english_p016_img04.png",
        "output\\images\\floor_puzzle_chapter_wise_dpp_english\\floor_puzzle_chapter_wise_dpp_english_p016_img05.png"
      ]
    },
    {
      "page_number": 17,
      "used_ocr": false,
      "text": "CASE 2 (b)\nCASE 3\nCASE 4\n8. See solution number 7.\n9. Two people live between R and Q.\n10. R neither lives above J nor M. Therefore, case\n2(b), Case 3 and Case 4 are no longer valid.\nCASE 1\nCASE 2 (a)",
      "tables": [],
      "images": [
        "output\\images\\floor_puzzle_chapter_wise_dpp_english\\floor_puzzle_chapter_wise_dpp_english_p017_img01.png",
        "output\\images\\floor_puzzle_chapter_wise_dpp_english\\floor_puzzle_chapter_wise_dpp_english_p017_img02.png",
        "output\\images\\floor_puzzle_chapter_wise_dpp_english\\floor_puzzle_chapter_wise_dpp_english_p017_img03.png",
        "output\\images\\floor_puzzle_chapter_wise_dpp_english\\floor_puzzle_chapter_wise_dpp_english_p017_img04.png",
        "output\\images\\floor_puzzle_chapter_wise_dpp_english\\floor_puzzle_chapter_wise_dpp_english_p017_img05.png"
      ]
    },
    {
      "page_number": 18,
      "used_ocr": false,
      "text": "11. Three people live between P and L. Therefore,\ncase 2 (a) is no longer valid.\n12. L lives below J.\nCASE 1\nQ6\nText Solution:\n1. J lives on an odd number floor below floor 7.\n2. Two people live between J and M.\n3. M doesn’t live on the ground floor.\nCASE 1\nCASE 2\nCASE 3\nCASE 4",
      "tables": [],
      "images": [
        "output\\images\\floor_puzzle_chapter_wise_dpp_english\\floor_puzzle_chapter_wise_dpp_english_p018_img01.png",
        "output\\images\\floor_puzzle_chapter_wise_dpp_english\\floor_puzzle_chapter_wise_dpp_english_p018_img02.png",
        "output\\images\\floor_puzzle_chapter_wise_dpp_english\\floor_puzzle_chapter_wise_dpp_english_p018_img03.png",
        "output\\images\\floor_puzzle_chapter_wise_dpp_english\\floor_puzzle_chapter_wise_dpp_english_p018_img04.png",
        "output\\images\\floor_puzzle_chapter_wise_dpp_english\\floor_puzzle_chapter_wise_dpp_english_p018_img05.png"
      ]
    },
    {
      "page_number": 19,
      "used_ocr": false,
      "text": "4. Three people live between K and N.\n5. K lives above N.\n6. Two people live between O and N.\n7. Q lives below N but above O.\nCASE 1\nCASE 2 (a)\nCASE 2 (b)\nCASE 3\nCASE 4",
      "tables": [],
      "images": [
        "output\\images\\floor_puzzle_chapter_wise_dpp_english\\floor_puzzle_chapter_wise_dpp_english_p019_img01.png",
        "output\\images\\floor_puzzle_chapter_wise_dpp_english\\floor_puzzle_chapter_wise_dpp_english_p019_img02.png",
        "output\\images\\floor_puzzle_chapter_wise_dpp_english\\floor_puzzle_chapter_wise_dpp_english_p019_img03.png",
        "output\\images\\floor_puzzle_chapter_wise_dpp_english\\floor_puzzle_chapter_wise_dpp_english_p019_img04.png",
        "output\\images\\floor_puzzle_chapter_wise_dpp_english\\floor_puzzle_chapter_wise_dpp_english_p019_img05.png"
      ]
    },
    {
      "page_number": 20,
      "used_ocr": false,
      "text": "8. See solution number 7.\n9. Two people live between R and Q.\n10. R neither lives above J nor M. Therefore, case\n2(b), Case 3 and Case 4 are no longer valid.\nCASE 1\nCASE 2 (a)\n11. Three people live between P and L. Therefore,\ncase 2 (a) is no longer valid.\n12. L lives below J.\nCASE 1\nQ7\nText Solution:\n1. J lives on an odd number floor below floor 7.\n2. Two people live between J and M.\n3. M doesn’t live on the ground floor.\nCASE 1",
      "tables": [],
      "images": [
        "output\\images\\floor_puzzle_chapter_wise_dpp_english\\floor_puzzle_chapter_wise_dpp_english_p020_img01.png",
        "output\\images\\floor_puzzle_chapter_wise_dpp_english\\floor_puzzle_chapter_wise_dpp_english_p020_img02.png",
        "output\\images\\floor_puzzle_chapter_wise_dpp_english\\floor_puzzle_chapter_wise_dpp_english_p020_img03.png",
        "output\\images\\floor_puzzle_chapter_wise_dpp_english\\floor_puzzle_chapter_wise_dpp_english_p020_img04.png"
      ]
    },
    {
      "page_number": 21,
      "used_ocr": false,
      "text": "CASE 2\nCASE 3\nCASE 4\n4. Three people live between K and N.\n5. K lives above N.\n6. Two people live between O and N.\n7. Q lives below N but above O.\nCASE 1\nCASE 2 (a)",
      "tables": [],
      "images": [
        "output\\images\\floor_puzzle_chapter_wise_dpp_english\\floor_puzzle_chapter_wise_dpp_english_p021_img01.png",
        "output\\images\\floor_puzzle_chapter_wise_dpp_english\\floor_puzzle_chapter_wise_dpp_english_p021_img02.png",
        "output\\images\\floor_puzzle_chapter_wise_dpp_english\\floor_puzzle_chapter_wise_dpp_english_p021_img03.png",
        "output\\images\\floor_puzzle_chapter_wise_dpp_english\\floor_puzzle_chapter_wise_dpp_english_p021_img04.png",
        "output\\images\\floor_puzzle_chapter_wise_dpp_english\\floor_puzzle_chapter_wise_dpp_english_p021_img05.png"
      ]
    },
    {
      "page_number": 22,
      "used_ocr": false,
      "text": "CASE 2 (b)\nCASE 3\nCASE 4\n8. See solution number 7.\n9. Two people live between R and Q.\n10. R neither lives above J nor M. Therefore, case\n2(b), Case 3 and Case 4 are no longer valid.\nCASE 1\nCASE 2 (a)",
      "tables": [],
      "images": [
        "output\\images\\floor_puzzle_chapter_wise_dpp_english\\floor_puzzle_chapter_wise_dpp_english_p022_img01.png",
        "output\\images\\floor_puzzle_chapter_wise_dpp_english\\floor_puzzle_chapter_wise_dpp_english_p022_img02.png",
        "output\\images\\floor_puzzle_chapter_wise_dpp_english\\floor_puzzle_chapter_wise_dpp_english_p022_img03.png",
        "output\\images\\floor_puzzle_chapter_wise_dpp_english\\floor_puzzle_chapter_wise_dpp_english_p022_img04.png",
        "output\\images\\floor_puzzle_chapter_wise_dpp_english\\floor_puzzle_chapter_wise_dpp_english_p022_img05.png"
      ]
    },
    {
      "page_number": 23,
      "used_ocr": false,
      "text": "11. Three people live between P and L. Therefore,\ncase 2 (a) is no longer valid.\n12. L lives below J.\nCASE 1\nQ8\nText Solution:\n1. J lives on an odd number floor below floor 7.\n2. Two people live between J and M.\n3. M doesn’t live on the ground floor.\nCASE 1\nCASE 2\nCASE 3\nCASE 4",
      "tables": [],
      "images": [
        "output\\images\\floor_puzzle_chapter_wise_dpp_english\\floor_puzzle_chapter_wise_dpp_english_p023_img01.png",
        "output\\images\\floor_puzzle_chapter_wise_dpp_english\\floor_puzzle_chapter_wise_dpp_english_p023_img02.png",
        "output\\images\\floor_puzzle_chapter_wise_dpp_english\\floor_puzzle_chapter_wise_dpp_english_p023_img03.png",
        "output\\images\\floor_puzzle_chapter_wise_dpp_english\\floor_puzzle_chapter_wise_dpp_english_p023_img04.png",
        "output\\images\\floor_puzzle_chapter_wise_dpp_english\\floor_puzzle_chapter_wise_dpp_english_p023_img05.png"
      ]
    },
    {
      "page_number": 24,
      "used_ocr": false,
      "text": "4. Three people live between K and N.\n5. K lives above N.\n6. Two people live between O and N.\n7. Q lives below N but above O.\nCASE 1\nCASE 2 (a)\nCASE 2 (b)\nCASE 3\nCASE 4",
      "tables": [],
      "images": [
        "output\\images\\floor_puzzle_chapter_wise_dpp_english\\floor_puzzle_chapter_wise_dpp_english_p024_img01.png",
        "output\\images\\floor_puzzle_chapter_wise_dpp_english\\floor_puzzle_chapter_wise_dpp_english_p024_img02.png",
        "output\\images\\floor_puzzle_chapter_wise_dpp_english\\floor_puzzle_chapter_wise_dpp_english_p024_img03.png",
        "output\\images\\floor_puzzle_chapter_wise_dpp_english\\floor_puzzle_chapter_wise_dpp_english_p024_img04.png",
        "output\\images\\floor_puzzle_chapter_wise_dpp_english\\floor_puzzle_chapter_wise_dpp_english_p024_img05.png"
      ]
    },
    {
      "page_number": 25,
      "used_ocr": false,
      "text": "8. See solution number 7.\n9. Two people live between R and Q.\n10. R neither lives above J nor M. Therefore, case\n2(b), Case 3 and Case 4 are no longer valid.\nCASE 1\nCASE 2 (a)\n11. Three people live between P and L. Therefore,\ncase 2 (a) is no longer valid.\n12. L lives below J.\nCASE 1\nQ9\nText Solution:\n1. J lives on an odd number floor below floor 7.\n2. Two people live between J and M.\n3. M doesn’t live on the ground floor.\nCASE 1",
      "tables": [],
      "images": [
        "output\\images\\floor_puzzle_chapter_wise_dpp_english\\floor_puzzle_chapter_wise_dpp_english_p025_img01.png",
        "output\\images\\floor_puzzle_chapter_wise_dpp_english\\floor_puzzle_chapter_wise_dpp_english_p025_img02.png",
        "output\\images\\floor_puzzle_chapter_wise_dpp_english\\floor_puzzle_chapter_wise_dpp_english_p025_img03.png",
        "output\\images\\floor_puzzle_chapter_wise_dpp_english\\floor_puzzle_chapter_wise_dpp_english_p025_img04.png"
      ]
    },
    {
      "page_number": 26,
      "used_ocr": false,
      "text": "CASE 2\nCASE 3\nCASE 4\n4. Three people live between K and N.\n5. K lives above N.\n6. Two people live between O and N.\n7. Q lives below N but above O.\nCASE 1\nCASE 2 (a)",
      "tables": [],
      "images": [
        "output\\images\\floor_puzzle_chapter_wise_dpp_english\\floor_puzzle_chapter_wise_dpp_english_p026_img01.png",
        "output\\images\\floor_puzzle_chapter_wise_dpp_english\\floor_puzzle_chapter_wise_dpp_english_p026_img02.png",
        "output\\images\\floor_puzzle_chapter_wise_dpp_english\\floor_puzzle_chapter_wise_dpp_english_p026_img03.png",
        "output\\images\\floor_puzzle_chapter_wise_dpp_english\\floor_puzzle_chapter_wise_dpp_english_p026_img04.png",
        "output\\images\\floor_puzzle_chapter_wise_dpp_english\\floor_puzzle_chapter_wise_dpp_english_p026_img05.png"
      ]
    },
    {
      "page_number": 27,
      "used_ocr": false,
      "text": "CASE 2 (b)\nCASE 3\nCASE 4\n8. See solution number 7.\n9. Two people live between R and Q.\n10. R neither lives above J nor M. Therefore, case\n2(b), Case 3 and Case 4 are no longer valid.\nCASE 1\nCASE 2 (a)",
      "tables": [],
      "images": [
        "output\\images\\floor_puzzle_chapter_wise_dpp_english\\floor_puzzle_chapter_wise_dpp_english_p027_img01.png",
        "output\\images\\floor_puzzle_chapter_wise_dpp_english\\floor_puzzle_chapter_wise_dpp_english_p027_img02.png",
        "output\\images\\floor_puzzle_chapter_wise_dpp_english\\floor_puzzle_chapter_wise_dpp_english_p027_img03.png",
        "output\\images\\floor_puzzle_chapter_wise_dpp_english\\floor_puzzle_chapter_wise_dpp_english_p027_img04.png",
        "output\\images\\floor_puzzle_chapter_wise_dpp_english\\floor_puzzle_chapter_wise_dpp_english_p027_img05.png"
      ]
    },
    {
      "page_number": 28,
      "used_ocr": false,
      "text": "11. Three people live between P and L. Therefore,\ncase 2 (a) is no longer valid.\n12. L lives below J.\nCASE 1\nQ10\nText Solution:\n1. O lives on the fifth floor.\n2. Two people live between O and Q.\n3. Three people live between Q and J.\nCASE 1\nCASE 2\n4. Two people live between J and L.\n5. L does not live on the topmost floor.\nCASE 1",
      "tables": [],
      "images": [
        "output\\images\\floor_puzzle_chapter_wise_dpp_english\\floor_puzzle_chapter_wise_dpp_english_p028_img01.png",
        "output\\images\\floor_puzzle_chapter_wise_dpp_english\\floor_puzzle_chapter_wise_dpp_english_p028_img02.png",
        "output\\images\\floor_puzzle_chapter_wise_dpp_english\\floor_puzzle_chapter_wise_dpp_english_p028_img03.png",
        "output\\images\\floor_puzzle_chapter_wise_dpp_english\\floor_puzzle_chapter_wise_dpp_english_p028_img04.png"
      ]
    },
    {
      "page_number": 29,
      "used_ocr": false,
      "text": "CASE 2 (a)\nCASE 2 (b)\n6. N lives above M.\n7. Two people live between N and R.\n8. Two people live between R and M.\n9. M neither lives on the topmost floor nor on\nthe lowermost floor.\nCASE 1\nCASE 2 (a)",
      "tables": [],
      "images": [
        "output\\images\\floor_puzzle_chapter_wise_dpp_english\\floor_puzzle_chapter_wise_dpp_english_p029_img01.png",
        "output\\images\\floor_puzzle_chapter_wise_dpp_english\\floor_puzzle_chapter_wise_dpp_english_p029_img02.png",
        "output\\images\\floor_puzzle_chapter_wise_dpp_english\\floor_puzzle_chapter_wise_dpp_english_p029_img03.png",
        "output\\images\\floor_puzzle_chapter_wise_dpp_english\\floor_puzzle_chapter_wise_dpp_english_p029_img04.png"
      ]
    },
    {
      "page_number": 30,
      "used_ocr": false,
      "text": "CASE 2 (b)\n10. M doesn’t live below P. Therefore, case 1 is no\nlonger valid.\n11. K lives above L. Therefore, Case 2 (a) is no\nlonger valid.\nCASE 2 (b)\nQ11\nText Solution:\n1. S lives on floor number 6.\n2. Two people live between S and X.\nCASE 1\nCASE 2",
      "tables": [],
      "images": [
        "output\\images\\floor_puzzle_chapter_wise_dpp_english\\floor_puzzle_chapter_wise_dpp_english_p030_img01.png",
        "output\\images\\floor_puzzle_chapter_wise_dpp_english\\floor_puzzle_chapter_wise_dpp_english_p030_img02.png",
        "output\\images\\floor_puzzle_chapter_wise_dpp_english\\floor_puzzle_chapter_wise_dpp_english_p030_img03.png",
        "output\\images\\floor_puzzle_chapter_wise_dpp_english\\floor_puzzle_chapter_wise_dpp_english_p030_img04.png",
        "output\\images\\floor_puzzle_chapter_wise_dpp_english\\floor_puzzle_chapter_wise_dpp_english_p030_img05.png"
      ]
    },
    {
      "page_number": 31,
      "used_ocr": false,
      "text": "3. A lives three floors above T.\n4. Two people live between T and Z.\n5. T lives above Z.\n6. T doesn’t live immediately below S.\n7. X lives above W.\nCASE 1\nCASE 2\n8. Two people live between V and Y.\n9. A lives below V.\n10. U lives below W. Therefore, case 1 is no longer\nvalid.\nCASE 2\nQ12\nText Solution:\nFour persons are living between M and V. M is\nliving above V. V is living immediately above R.\nSo, we get two possible cases: -\nFloors\nPersons Persons\nCase 1\nCase 2\n8\nM\n \n7\n \nM\n6\n \n \n5\n \n \n4\n \n \n3\nV\n \n2\nR\nV\n1\n \nR\nY lives below R. So, case 2 is cancelled here: -\nFloors\nPersons Persons\nCase 1\nCase 2\n8\nM\n \n7\n \nM\n6\n \n \n5\n \n \n4\n \n \n3\nV\n \n2\nR\nV\n1\nY\nR\nA neither lives on an odd-numbered floor nor on\ntop most floor. Three persons are living between\nP and R. One person lives between V and G. We",
      "tables": [
        {
          "headers": [
            "Floors",
            "Persons",
            "Persons"
          ],
          "rows": [
            [
              "",
              "Case 1",
              "Case 2"
            ],
            [
              "8",
              "M",
              ""
            ],
            [
              "7",
              "",
              "M"
            ],
            [
              "6",
              "",
              ""
            ],
            [
              "5",
              "",
              ""
            ],
            [
              "4",
              "",
              ""
            ],
            [
              "3",
              "V",
              ""
            ],
            [
              "2",
              "R",
              "V"
            ],
            [
              "1",
              "",
              "R"
            ]
          ]
        },
        {
          "headers": [
            "Floors",
            "Persons",
            ""
          ],
          "rows": [
            [
              "",
              "",
              "Persons"
            ],
            [
              "",
              "Case 1",
              "Case 2"
            ],
            [
              "8",
              "M",
              ""
            ],
            [
              "7",
              "",
              "M"
            ],
            [
              "6",
              "",
              ""
            ],
            [
              "5",
              "",
              ""
            ],
            [
              "4",
              "",
              ""
            ],
            [
              "3",
              "V",
              ""
            ],
            [
              "2",
              "R",
              "V"
            ],
            [
              "1",
              "Y",
              "R"
            ]
          ]
        }
      ],
      "images": [
        "output\\images\\floor_puzzle_chapter_wise_dpp_english\\floor_puzzle_chapter_wise_dpp_english_p031_img01.png",
        "output\\images\\floor_puzzle_chapter_wise_dpp_english\\floor_puzzle_chapter_wise_dpp_english_p031_img02.png",
        "output\\images\\floor_puzzle_chapter_wise_dpp_english\\floor_puzzle_chapter_wise_dpp_english_p031_img03.png"
      ]
    },
    {
      "page_number": 32,
      "used_ocr": false,
      "text": "know, J is one of the persons thus the final\narrangement is: -\nFloors\nPersons\n8\nM\n7\nJ\n6\nP\n5\nG\n4\nA\n3\nV\n2\nR\n1\nY\n \nQ13\nText Solution:\nFour persons are living between M and V. M is\nliving above V. V is living immediately above R.\nSo, we get two possible cases: -\nFloors\nPersons Persons\nCase 1\nCase 2\n8\nM\n \n7\n \nM\n6\n \n \n5\n \n \n4\n \n \n3\nV\n \n2\nR\nV\n1\n \nR\nY lives below R. So, case 2 is cancelled here: -\nFloors\nPersons Persons\nCase 1\nCase 2\n8\nM\n \n7\n \nM\n6\n \n \n5\n \n \n4\n \n \n3\nV\n \n2\nR\nV\n1\nY\nR\nA neither lives on an odd-numbered floor nor on\ntop most floor. Three persons are living between\nP and R. One person lives between V and G. We\nknow, J is one of the persons thus the final\narrangement is: -\nFloors\nPersons\n8\nM\n7\nJ\n6\nP\n5\nG\n4\nA\n3\nV\n2\nR\n1\nY\n \nQ14\nText Solution:\nFour persons are living between M and V. M is\nliving above V. V is living immediately above R.\nSo, we get two possible cases: -\nFloors\nPersons Persons\nCase 1\nCase 2\n8\nM\n \n7\n \nM\n6\n \n \n5\n \n \n4\n \n \n3\nV\n \n2\nR\nV\n1\n \nR\nY lives below R. So, case 2 is cancelled here: -\nFloors\nPersons Persons\nCase 1\nCase 2\n8\nM\n \n7\n \nM\n6\n \n \n5\n \n \n4\n \n \n3\nV\n \n2\nR\nV\n1\nY\nR\nA neither lives on an odd-numbered floor nor on\ntop most floor. Three persons are living between\nP and R. One person lives between V and G. We",
      "tables": [
        {
          "headers": [
            "Floors",
            "Persons"
          ],
          "rows": [
            [
              "8",
              "M"
            ],
            [
              "7",
              "J"
            ],
            [
              "6",
              "P"
            ],
            [
              "5",
              "G"
            ],
            [
              "4",
              "A"
            ],
            [
              "3",
              "V"
            ],
            [
              "2",
              "R"
            ],
            [
              "1",
              "Y"
            ]
          ]
        },
        {
          "headers": [
            "Floors",
            "Persons"
          ],
          "rows": [
            [
              "8",
              "M"
            ],
            [
              "7",
              "J"
            ],
            [
              "6",
              "P"
            ],
            [
              "5",
              "G"
            ],
            [
              "4",
              "A"
            ],
            [
              "3",
              "V"
            ],
            [
              "2",
              "R"
            ],
            [
              "1",
              "Y"
            ]
          ]
        },
        {
          "headers": [
            "Floors",
            "Persons",
            "Persons"
          ],
          "rows": [
            [
              "",
              "Case 1",
              "Case 2"
            ],
            [
              "8",
              "M",
              ""
            ],
            [
              "7",
              "",
              "M"
            ],
            [
              "6",
              "",
              ""
            ],
            [
              "5",
              "",
              ""
            ],
            [
              "4",
              "",
              ""
            ],
            [
              "3",
              "V",
              ""
            ],
            [
              "2",
              "R",
              "V"
            ],
            [
              "1",
              "",
              "R"
            ]
          ]
        },
        {
          "headers": [
            "Floors",
            "Persons",
            "Persons"
          ],
          "rows": [
            [
              "",
              "Case 1",
              "Case 2"
            ],
            [
              "8",
              "M",
              ""
            ],
            [
              "7",
              "",
              "M"
            ],
            [
              "6",
              "",
              ""
            ],
            [
              "5",
              "",
              ""
            ],
            [
              "4",
              "",
              ""
            ],
            [
              "3",
              "V",
              ""
            ],
            [
              "2",
              "R",
              "V"
            ],
            [
              "1",
              "",
              "R"
            ]
          ]
        },
        {
          "headers": [
            "Floors",
            "Persons",
            ""
          ],
          "rows": [
            [
              "",
              "",
              "Persons"
            ],
            [
              "",
              "Case 1",
              "Case 2"
            ],
            [
              "8",
              "M",
              ""
            ],
            [
              "7",
              "",
              "M"
            ],
            [
              "6",
              "",
              ""
            ],
            [
              "5",
              "",
              ""
            ],
            [
              "4",
              "",
              ""
            ],
            [
              "3",
              "V",
              ""
            ],
            [
              "2",
              "R",
              "V"
            ],
            [
              "1",
              "Y",
              "R"
            ]
          ]
        },
        {
          "headers": [
            "Floors",
            "Persons",
            ""
          ],
          "rows": [
            [
              "",
              "",
              "Persons"
            ],
            [
              "",
              "Case 1",
              "Case 2"
            ],
            [
              "8",
              "M",
              ""
            ],
            [
              "7",
              "",
              "M"
            ],
            [
              "6",
              "",
              ""
            ],
            [
              "5",
              "",
              ""
            ],
            [
              "4",
              "",
              ""
            ],
            [
              "3",
              "V",
              ""
            ],
            [
              "2",
              "R",
              "V"
            ],
            [
              "1",
              "Y",
              "R"
            ]
          ]
        }
      ],
      "images": []
    },
    {
      "page_number": 33,
      "used_ocr": false,
      "text": "know, J is one of the persons thus the final\narrangement is: -\nFloors\nPersons\n8\nM\n7\nJ\n6\nP\n5\nG\n4\nA\n3\nV\n2\nR\n1\nY\n \nQ15\nText Solution:\nFour persons are living between M and V. M is\nliving above V. V is living immediately above R.\nSo, we get two possible cases: -\nFloors\nPersons Persons\nCase 1\nCase 2\n8\nM\n \n7\n \nM\n6\n \n \n5\n \n \n4\n \n \n3\nV\n \n2\nR\nV\n1\n \nR\nY lives below R. So, case 2 is cancelled here: -\nFloors\nPersons Persons\nCase 1\nCase 2\n8\nM\n \n7\n \nM\n6\n \n \n5\n \n \n4\n \n \n3\nV\n \n2\nR\nV\n1\nY\nR\nA neither lives on an odd-numbered floor nor on\ntop most floor. Three persons are living between\nP and R. One person lives between V and G. We\nknow, J is one of the persons thus the final\narrangement is: -\nFloors\nPersons\n8\nM\n7\nJ\n6\nP\n5\nG\n4\nA\n3\nV\n2\nR\n1\nY\n \nQ16\nText Solution:\nFour persons are living between M and V. M is\nliving above V. V is living immediately above R.\nSo, we get two possible cases: -\nFloors\nPersons Persons\nCase 1\nCase 2\n8\nM\n \n7\n \nM\n6\n \n \n5\n \n \n4\n \n \n3\nV\n \n2\nR\nV\n1\n \nR\nY lives below R. So, case 2 is cancelled here: -\nFloors\nPersons Persons\nCase 1\nCase 2\n8\nM\n \n7\n \nM\n6\n \n \n5\n \n \n4\n \n \n3\nV\n \n2\nR\nV\n1\nY\nR\nA neither lives on an odd-numbered floor nor on\ntop most floor. Three persons are living between\nP and R. One person lives between V and G. We",
      "tables": [
        {
          "headers": [
            "Floors",
            "Persons"
          ],
          "rows": [
            [
              "8",
              "M"
            ],
            [
              "7",
              "J"
            ],
            [
              "6",
              "P"
            ],
            [
              "5",
              "G"
            ],
            [
              "4",
              "A"
            ],
            [
              "3",
              "V"
            ],
            [
              "2",
              "R"
            ],
            [
              "1",
              "Y"
            ]
          ]
        },
        {
          "headers": [
            "Floors",
            "Persons"
          ],
          "rows": [
            [
              "8",
              "M"
            ],
            [
              "7",
              "J"
            ],
            [
              "6",
              "P"
            ],
            [
              "5",
              "G"
            ],
            [
              "4",
              "A"
            ],
            [
              "3",
              "V"
            ],
            [
              "2",
              "R"
            ],
            [
              "1",
              "Y"
            ]
          ]
        },
        {
          "headers": [
            "Floors",
            "Persons",
            "Persons"
          ],
          "rows": [
            [
              "",
              "Case 1",
              "Case 2"
            ],
            [
              "8",
              "M",
              ""
            ],
            [
              "7",
              "",
              "M"
            ],
            [
              "6",
              "",
              ""
            ],
            [
              "5",
              "",
              ""
            ],
            [
              "4",
              "",
              ""
            ],
            [
              "3",
              "V",
              ""
            ],
            [
              "2",
              "R",
              "V"
            ],
            [
              "1",
              "",
              "R"
            ]
          ]
        },
        {
          "headers": [
            "Floors",
            "Persons",
            "Persons"
          ],
          "rows": [
            [
              "",
              "Case 1",
              "Case 2"
            ],
            [
              "8",
              "M",
              ""
            ],
            [
              "7",
              "",
              "M"
            ],
            [
              "6",
              "",
              ""
            ],
            [
              "5",
              "",
              ""
            ],
            [
              "4",
              "",
              ""
            ],
            [
              "3",
              "V",
              ""
            ],
            [
              "2",
              "R",
              "V"
            ],
            [
              "1",
              "",
              "R"
            ]
          ]
        },
        {
          "headers": [
            "Floors",
            "Persons",
            ""
          ],
          "rows": [
            [
              "",
              "",
              "Persons"
            ],
            [
              "",
              "Case 1",
              "Case 2"
            ],
            [
              "8",
              "M",
              ""
            ],
            [
              "7",
              "",
              "M"
            ],
            [
              "6",
              "",
              ""
            ],
            [
              "5",
              "",
              ""
            ],
            [
              "4",
              "",
              ""
            ],
            [
              "3",
              "V",
              ""
            ],
            [
              "2",
              "R",
              "V"
            ],
            [
              "1",
              "Y",
              "R"
            ]
          ]
        },
        {
          "headers": [
            "Floors",
            "Persons",
            ""
          ],
          "rows": [
            [
              "",
              "",
              "Persons"
            ],
            [
              "",
              "Case 1",
              "Case 2"
            ],
            [
              "8",
              "M",
              ""
            ],
            [
              "7",
              "",
              "M"
            ],
            [
              "6",
              "",
              ""
            ],
            [
              "5",
              "",
              ""
            ],
            [
              "4",
              "",
              ""
            ],
            [
              "3",
              "V",
              ""
            ],
            [
              "2",
              "R",
              "V"
            ],
            [
              "1",
              "Y",
              "R"
            ]
          ]
        }
      ],
      "images": []
    },
    {
      "page_number": 34,
      "used_ocr": false,
      "text": "know, J is one of the persons thus the final\narrangement is: -\nFloors\nPersons\n8\nM\n7\nJ\n6\nP\n5\nG\n4\nA\n3\nV\n2\nR\n1\nY\n \nQ17\nText Solution:\nQ is living on the floor number 3\nM is living on an even-numbered floor above\nthe floor number 6 \nThree persons are living between the floors on\nwhich M and P are living\nOnly four persons are living between the\nfloors on which P and O are living\n \nCase-1 Case-2\nFloors Persons Persons\n10\nM\n \n9\n \nO\n8\n \nM\n7\n \n \n6\nP\n \n5\n \n \n4\n \nP\n3\nQ\nQ\n2\n \n \n1\nO\n \n \nK is living immediately above the floor on\nwhich O is living\n \nCase-1 Case-2\nFloors Persons Persons\n10\nM\nK\n9\n \nO\n8\n \nM\n7\n \n \n6\nP\n \n5\n \n \n4\n \nP\n3\nQ\nQ\n2\nK\n \n1\nO\n \n \nThere is only one floor between the floor on\nwhich P is living and the floor on which J is\nliving\nJ is living above P\nL is living immediately above Q, therefore,\nCase-2 will get eliminated\nN is living above I but below J\nFloors Persons\n10\nM\n9\nR\n8\nJ\n7\nN\n6\nP\n5\nI\n4\nL\n3\nQ\n2\nK\n1\nO\nThis is the final arrangement.\nQ18\nText Solution:\nQ is living on the floor number 3\nM is living on an even-numbered floor above\nthe floor number 6 \nThree persons are living between the floors on\nwhich M and P are living\nOnly four persons are living between the\nfloors on which P and O are living\n \nCase-1 Case-2\nFloors Persons Persons\n10\nM\n \n9\n \nO\n8\n \nM",
      "tables": [
        {
          "headers": [
            "7",
            "",
            ""
          ],
          "rows": [
            [
              "6",
              "P",
              ""
            ],
            [
              "5",
              "",
              ""
            ],
            [
              "4",
              "",
              "P"
            ],
            [
              "3",
              "Q",
              "Q"
            ],
            [
              "2",
              "K",
              ""
            ],
            [
              "1",
              "O",
              ""
            ]
          ]
        },
        {
          "headers": [
            "Floors",
            "Persons"
          ],
          "rows": [
            [
              "8",
              "M"
            ],
            [
              "7",
              "J"
            ],
            [
              "6",
              "P"
            ],
            [
              "5",
              "G"
            ],
            [
              "4",
              "A"
            ],
            [
              "3",
              "V"
            ],
            [
              "2",
              "R"
            ],
            [
              "1",
              "Y"
            ]
          ]
        },
        {
          "headers": [
            "Floors",
            "Persons"
          ],
          "rows": [
            [
              "10",
              "M"
            ],
            [
              "9",
              "R"
            ],
            [
              "8",
              "J"
            ],
            [
              "7",
              "N"
            ],
            [
              "6",
              "P"
            ],
            [
              "5",
              "I"
            ],
            [
              "4",
              "L"
            ],
            [
              "3",
              "Q"
            ],
            [
              "2",
              "K"
            ],
            [
              "1",
              "O"
            ]
          ]
        },
        {
          "headers": [
            "",
            "Case-1",
            "Case-2"
          ],
          "rows": [
            [
              "Floors",
              "Persons",
              "Persons"
            ],
            [
              "10",
              "M",
              ""
            ],
            [
              "9",
              "",
              "O"
            ],
            [
              "8",
              "",
              "M"
            ],
            [
              "7",
              "",
              ""
            ],
            [
              "6",
              "P",
              ""
            ],
            [
              "5",
              "",
              ""
            ],
            [
              "4",
              "",
              "P"
            ],
            [
              "3",
              "Q",
              "Q"
            ],
            [
              "2",
              "",
              ""
            ],
            [
              "1",
              "O",
              ""
            ]
          ]
        },
        {
          "headers": [
            "",
            "Case-1",
            "Case-2"
          ],
          "rows": [
            [
              "Floors",
              "Persons",
              "Persons"
            ],
            [
              "10",
              "M",
              ""
            ],
            [
              "9",
              "",
              "O"
            ],
            [
              "8",
              "",
              "M"
            ]
          ]
        },
        {
          "headers": [
            "",
            "Case-1",
            "Case-2"
          ],
          "rows": [
            [
              "Floors",
              "Persons",
              "Persons"
            ],
            [
              "10",
              "M",
              "K"
            ],
            [
              "9",
              "",
              "O"
            ],
            [
              "8",
              "",
              "M"
            ]
          ]
        }
      ],
      "images": []
    },
    {
      "page_number": 35,
      "used_ocr": false,
      "text": "7\n \n \n6\nP\n \n5\n \n \n4\n \nP\n3\nQ\nQ\n2\n \n \n1\nO\n \nK is living immediately above the floor on\nwhich O is living\n \nCase-1 Case-2\nFloors Persons Persons\n10\nM\nK\n9\n \nO\n8\n \nM\n7\n \n \n6\nP\n \n5\n \n \n4\n \nP\n3\nQ\nQ\n2\nK\n \n1\nO\n \nThere is only one floor between the floor on\nwhich P is living and the floor on which J is\nliving\nJ is living above P\nL is living immediately above Q, therefore,\nCase-2 will get eliminated\nN is living above I but below J\nFloors Persons\n10\nM\n9\nR\n8\nJ\n7\nN\n6\nP\n5\nI\n4\nL\n3\nQ\n2\nK\n1\nO\nThis is the final arrangement.\nHence, J lives on the 8th floor.\nQ19\nText Solution:\nQ is living on the floor number 3\nM is living on an even-numbered floor above\nthe floor number 6 \nThree persons are living between the floors on\nwhich M and P are living\nOnly four persons are living between the\nfloors on which P and O are living\n \nCase-1 Case-2\nFloors Persons Persons\n10\nM\n \n9\n \nO\n8\n \nM\n7\n \n \n6\nP\n \n5\n \n \n4\n \nP\n3\nQ\nQ\n2\n \n \n1\nO\n \n \nK is living immediately above the floor on\nwhich O is living\n \nCase-1 Case-2\nFloors Persons Persons\n10\nM\nK\n9\n \nO\n8\n \nM\n7\n \n \n6\nP\n \n5\n \n \n4\n \nP\n3\nQ\nQ\n2\nK\n \n1\nO\n \n \nThere is only one floor between the floor on\nwhich P is living and the floor on which J is\nliving",
      "tables": [
        {
          "headers": [
            "7",
            "",
            ""
          ],
          "rows": [
            [
              "6",
              "P",
              ""
            ],
            [
              "5",
              "",
              ""
            ],
            [
              "4",
              "",
              "P"
            ],
            [
              "3",
              "Q",
              "Q"
            ],
            [
              "2",
              "",
              ""
            ],
            [
              "1",
              "O",
              ""
            ]
          ]
        },
        {
          "headers": [
            "",
            "Case-1",
            "Case-2"
          ],
          "rows": [
            [
              "Floors",
              "Persons",
              "Persons"
            ],
            [
              "10",
              "M",
              ""
            ],
            [
              "9",
              "",
              "O"
            ],
            [
              "8",
              "",
              "M"
            ],
            [
              "7",
              "",
              ""
            ],
            [
              "6",
              "P",
              ""
            ],
            [
              "5",
              "",
              ""
            ],
            [
              "4",
              "",
              "P"
            ],
            [
              "3",
              "Q",
              "Q"
            ],
            [
              "2",
              "",
              ""
            ],
            [
              "1",
              "O",
              ""
            ]
          ]
        },
        {
          "headers": [
            "",
            "Case-1",
            "Case-2"
          ],
          "rows": [
            [
              "Floors",
              "Persons",
              "Persons"
            ],
            [
              "10",
              "M",
              "K"
            ],
            [
              "9",
              "",
              "O"
            ],
            [
              "8",
              "",
              "M"
            ],
            [
              "7",
              "",
              ""
            ],
            [
              "6",
              "P",
              ""
            ],
            [
              "5",
              "",
              ""
            ],
            [
              "4",
              "",
              "P"
            ],
            [
              "3",
              "Q",
              "Q"
            ],
            [
              "2",
              "K",
              ""
            ],
            [
              "1",
              "O",
              ""
            ]
          ]
        },
        {
          "headers": [
            "",
            "Case-1",
            "Case-2"
          ],
          "rows": [
            [
              "Floors",
              "Persons",
              "Persons"
            ],
            [
              "10",
              "M",
              "K"
            ],
            [
              "9",
              "",
              "O"
            ],
            [
              "8",
              "",
              "M"
            ],
            [
              "7",
              "",
              ""
            ],
            [
              "6",
              "P",
              ""
            ],
            [
              "5",
              "",
              ""
            ],
            [
              "4",
              "",
              "P"
            ],
            [
              "3",
              "Q",
              "Q"
            ],
            [
              "2",
              "K",
              ""
            ],
            [
              "1",
              "O",
              ""
            ]
          ]
        },
        {
          "headers": [
            "Floors",
            "Persons"
          ],
          "rows": [
            [
              "10",
              "M"
            ],
            [
              "9",
              "R"
            ],
            [
              "8",
              "J"
            ],
            [
              "7",
              "N"
            ],
            [
              "6",
              "P"
            ],
            [
              "5",
              "I"
            ],
            [
              "4",
              "L"
            ],
            [
              "3",
              "Q"
            ],
            [
              "2",
              "K"
            ],
            [
              "1",
              "O"
            ]
          ]
        }
      ],
      "images": []
    },
    {
      "page_number": 36,
      "used_ocr": false,
      "text": "J is living above P\nL is living immediately above Q, therefore,\nCase-2 will get eliminated\nN is living above I but below J\nFloors Persons\n10\nM\n9\nR\n8\nJ\n7\nN\n6\nP\n5\nI\n4\nL\n3\nQ\n2\nK\n1\nO\nThis is the final arrangement.\nQ20\nText Solution:\nQ is living on the floor number 3\nM is living on an even-numbered floor above\nthe floor number 6 \nThree persons are living between the floors on\nwhich M and P are living\nOnly four persons are living between the\nfloors on which P and O are living\n \nCase-1 Case-2\nFloors Persons Persons\n10\nM\n \n9\n \nO\n8\n \nM\n7\n \n \n6\nP\n \n5\n \n \n4\n \nP\n3\nQ\nQ\n2\n \n \n1\nO\n \nK is living immediately above the floor on\nwhich O is living\n \nCase-1 Case-2\nFloors Persons Persons\n10\nM\nK\n9\n \nO\n8\n \nM\n7\n \n \n6\nP\n \n5\n \n \n4\n \nP\n3\nQ\nQ\n2\nK\n \n1\nO\n \nThere is only one floor between the floor on\nwhich P is living and the floor on which J is\nliving\nJ is living above P\nL is living immediately above Q, therefore,\nCase-2 will get eliminated\nN is living above I but below J\nFloors Persons\n10\nM\n9\nR\n8\nJ\n7\nN\n6\nP\n5\nI\n4\nL\n3\nQ\n2\nK\n1\nO\nThis is the final arrangement.\nHence, it is clear that \"N\" is living on floor 7.\nQ21\nText Solution:\nQ is living on the floor number 3\nM is living on an even-numbered floor above\nthe floor number 6 \nThree persons are living between the floors on\nwhich M and P are living\nOnly four persons are living between the\nfloors on which P and O are living\n \nCase-1 Case-2\nFloors Persons Persons",
      "tables": [
        {
          "headers": [
            "10",
            "M",
            "K"
          ],
          "rows": [
            [
              "9",
              "",
              "O"
            ],
            [
              "8",
              "",
              "M"
            ],
            [
              "7",
              "",
              ""
            ],
            [
              "6",
              "P",
              ""
            ],
            [
              "5",
              "",
              ""
            ],
            [
              "4",
              "",
              "P"
            ],
            [
              "3",
              "Q",
              "Q"
            ],
            [
              "2",
              "K",
              ""
            ],
            [
              "1",
              "O",
              ""
            ]
          ]
        },
        {
          "headers": [
            "Floors",
            "Persons"
          ],
          "rows": [
            [
              "10",
              "M"
            ],
            [
              "9",
              "R"
            ],
            [
              "8",
              "J"
            ],
            [
              "7",
              "N"
            ],
            [
              "6",
              "P"
            ],
            [
              "5",
              "I"
            ],
            [
              "4",
              "L"
            ],
            [
              "3",
              "Q"
            ],
            [
              "2",
              "K"
            ],
            [
              "1",
              "O"
            ]
          ]
        },
        {
          "headers": [
            "Floors",
            "Persons"
          ],
          "rows": [
            [
              "10",
              "M"
            ],
            [
              "9",
              "R"
            ],
            [
              "8",
              "J"
            ],
            [
              "7",
              "N"
            ],
            [
              "6",
              "P"
            ],
            [
              "5",
              "I"
            ],
            [
              "4",
              "L"
            ],
            [
              "3",
              "Q"
            ],
            [
              "2",
              "K"
            ],
            [
              "1",
              "O"
            ]
          ]
        },
        {
          "headers": [
            "",
            "Case-1",
            "Case-2"
          ],
          "rows": [
            [
              "Floors",
              "Persons",
              "Persons"
            ],
            [
              "10",
              "M",
              ""
            ],
            [
              "9",
              "",
              "O"
            ],
            [
              "8",
              "",
              "M"
            ],
            [
              "7",
              "",
              ""
            ],
            [
              "6",
              "P",
              ""
            ],
            [
              "5",
              "",
              ""
            ],
            [
              "4",
              "",
              "P"
            ],
            [
              "3",
              "Q",
              "Q"
            ],
            [
              "2",
              "",
              ""
            ],
            [
              "1",
              "O",
              ""
            ]
          ]
        },
        {
          "headers": [
            "",
            "Case-1",
            "Case-2"
          ],
          "rows": [
            [
              "Floors",
              "Persons",
              "Persons"
            ]
          ]
        },
        {
          "headers": [
            "",
            "Case-1",
            "Case-2"
          ],
          "rows": [
            [
              "Floors",
              "Persons",
              "Persons"
            ]
          ]
        }
      ],
      "images": []
    },
    {
      "page_number": 37,
      "used_ocr": false,
      "text": "10\nM\n \n9\n \nO\n8\n \nM\n7\n \n \n6\nP\n \n5\n \n \n4\n \nP\n3\nQ\nQ\n2\n \n \n1\nO\n \n \nK is living immediately above the floor on\nwhich O is living\n \nCase-1 Case-2\nFloors Persons Persons\n10\nM\nK\n9\n \nO\n8\n \nM\n7\n \n \n6\nP\n \n5\n \n \n4\n \nP\n3\nQ\nQ\n2\nK\n \n1\nO\n \n \nThere is only one floor between the floor on\nwhich P is living and the floor on which J is\nliving\nJ is living above P\nL is living immediately above Q, therefore,\nCase-2 will get eliminated\nN is living above I but below J\nFloors Persons\n10\nM\n9\nR\n8\nJ\n7\nN\n6\nP\n5\nI\n4\nL\n3\nQ\n2\nK\n1\nO\nThis is the final arrangement.\nQ22\nText Solution:\n1) Q lives on an even numbered floor.\n2) L lives below Y and above Q but not\nimmediately.\n3) L does not live on the fourth floor.\n4) Two people live between U, who lives above\nthe fourth floor and Y.\n5) Three people live between S and U.\n6) People lives between S and Q are more or less\nthan two.\n(Here, case 1 will be eliminated)\n7) X lives immediately above O, who lives below\nV.\nQ23\nText Solution:\n1) Q lives on an even numbered floor.\n2) L lives below Y and above Q but not\nimmediately.\n3) L does not live on the fourth floor.",
      "tables": [
        {
          "headers": [
            "10",
            "M",
            ""
          ],
          "rows": [
            [
              "9",
              "",
              "O"
            ],
            [
              "8",
              "",
              "M"
            ],
            [
              "7",
              "",
              ""
            ],
            [
              "6",
              "P",
              ""
            ],
            [
              "5",
              "",
              ""
            ],
            [
              "4",
              "",
              "P"
            ],
            [
              "3",
              "Q",
              "Q"
            ],
            [
              "2",
              "",
              ""
            ],
            [
              "1",
              "O",
              ""
            ]
          ]
        },
        {
          "headers": [
            "4",
            "L"
          ],
          "rows": [
            [
              "3",
              "Q"
            ],
            [
              "2",
              "K"
            ],
            [
              "1",
              "O"
            ]
          ]
        },
        {
          "headers": [
            "",
            "Case-1",
            "Case-2"
          ],
          "rows": [
            [
              "Floors",
              "Persons",
              "Persons"
            ],
            [
              "10",
              "M",
              "K"
            ],
            [
              "9",
              "",
              "O"
            ],
            [
              "8",
              "",
              "M"
            ],
            [
              "7",
              "",
              ""
            ],
            [
              "6",
              "P",
              ""
            ],
            [
              "5",
              "",
              ""
            ],
            [
              "4",
              "",
              "P"
            ],
            [
              "3",
              "Q",
              "Q"
            ],
            [
              "2",
              "K",
              ""
            ],
            [
              "1",
              "O",
              ""
            ]
          ]
        },
        {
          "headers": [
            "Floors",
            "Persons"
          ],
          "rows": [
            [
              "10",
              "M"
            ],
            [
              "9",
              "R"
            ],
            [
              "8",
              "J"
            ],
            [
              "7",
              "N"
            ],
            [
              "6",
              "P"
            ],
            [
              "5",
              "I"
            ]
          ]
        }
      ],
      "images": [
        "output\\images\\floor_puzzle_chapter_wise_dpp_english\\floor_puzzle_chapter_wise_dpp_english_p037_img01.png",
        "output\\images\\floor_puzzle_chapter_wise_dpp_english\\floor_puzzle_chapter_wise_dpp_english_p037_img02.png",
        "output\\images\\floor_puzzle_chapter_wise_dpp_english\\floor_puzzle_chapter_wise_dpp_english_p037_img03.png"
      ]
    },
    {
      "page_number": 38,
      "used_ocr": false,
      "text": "4) Two people live between U, who lives above\nthe fourth floor and Y.\n5) Three people live between S and U.\n6) People lives between S and Q are more or less\nthan two.\n(Here, case 1 will be eliminated)\n7) X lives immediately above O, who lives below\nV.\nQ24\nText Solution:\n1) Q lives on an even numbered floor.\n2) L lives below Y and above Q but not\nimmediately.\n3) L does not live on the fourth floor.\n4) Two people live between U, who lives above\nthe fourth floor and Y.\n5) Three people live between S and U.\n6) People lives between S and Q are more or less\nthan two.\n(Here, case 1 will be eliminated)\n7) X lives immediately above O, who lives below\nV.\nQ25\nText Solution:\n1) Q lives on an even numbered floor.\n2) L lives below Y and above Q but not\nimmediately.\n3) L does not live on the fourth floor.\n4) Two people live between U, who lives above\nthe fourth floor and Y.\n5) Three people live between S and U.\n6) People lives between S and Q are more or less\nthan two.\n(Here, case 1 will be eliminated)\n7) X lives immediately above O, who lives below\nV.",
      "tables": [],
      "images": [
        "output\\images\\floor_puzzle_chapter_wise_dpp_english\\floor_puzzle_chapter_wise_dpp_english_p038_img01.png",
        "output\\images\\floor_puzzle_chapter_wise_dpp_english\\floor_puzzle_chapter_wise_dpp_english_p038_img02.png",
        "output\\images\\floor_puzzle_chapter_wise_dpp_english\\floor_puzzle_chapter_wise_dpp_english_p038_img03.png",
        "output\\images\\floor_puzzle_chapter_wise_dpp_english\\floor_puzzle_chapter_wise_dpp_english_p038_img04.png",
        "output\\images\\floor_puzzle_chapter_wise_dpp_english\\floor_puzzle_chapter_wise_dpp_english_p038_img05.png",
        "output\\images\\floor_puzzle_chapter_wise_dpp_english\\floor_puzzle_chapter_wise_dpp_english_p038_img06.png",
        "output\\images\\floor_puzzle_chapter_wise_dpp_english\\floor_puzzle_chapter_wise_dpp_english_p038_img07.png",
        "output\\images\\floor_puzzle_chapter_wise_dpp_english\\floor_puzzle_chapter_wise_dpp_english_p038_img08.png"
      ]
    },
    {
      "page_number": 39,
      "used_ocr": false,
      "text": "Q26\nText Solution:\n1) Q lives on an even numbered floor.\n2) L lives below Y and above Q but not\nimmediately.\n3) L does not live on the fourth floor.\n4) Two people live between U, who lives above\nthe fourth floor and Y.\n5) Three people live between S and U.\n6) People lives between S and Q are more or less\nthan two.\n(Here, case 1 will be eliminated)\n7) X lives immediately above O, who lives below\nV.\nQ27\nText Solution:\nStarting point: Here, we can start with T, S and N\nin order to form two cases.\nClues: S lives two floors above N, who lives on\nodd numbered floor. T lives on bottommost floor.\nInference: So, N lives on either 3 or 5 floor.\nClues: P lives just above M and on the even\nnumbered floor. O lives above R’s floor but not\non the topmost floor. P doesn’t live on the\ntopmost floor.\nInference: So, case 1 would be rejected as P\ncannot be placed. So, Q must be living at\ntopmost floor.\nFour persons live between S’s and R’s floor.\nQ28\nText Solution:\nStarting point: Here, we can start with T, S and N\nin order to form two cases.\nClues: S lives two floors above N, who lives on\nodd numbered floor. T lives on bottommost floor.\n \nrd\nth",
      "tables": [],
      "images": [
        "output\\images\\floor_puzzle_chapter_wise_dpp_english\\floor_puzzle_chapter_wise_dpp_english_p039_img01.png",
        "output\\images\\floor_puzzle_chapter_wise_dpp_english\\floor_puzzle_chapter_wise_dpp_english_p039_img02.png",
        "output\\images\\floor_puzzle_chapter_wise_dpp_english\\floor_puzzle_chapter_wise_dpp_english_p039_img03.png",
        "output\\images\\floor_puzzle_chapter_wise_dpp_english\\floor_puzzle_chapter_wise_dpp_english_p039_img04.png",
        "output\\images\\floor_puzzle_chapter_wise_dpp_english\\floor_puzzle_chapter_wise_dpp_english_p039_img05.png",
        "output\\images\\floor_puzzle_chapter_wise_dpp_english\\floor_puzzle_chapter_wise_dpp_english_p039_img06.png"
      ]
    },
    {
      "page_number": 40,
      "used_ocr": false,
      "text": "Inference: So, N lives on either 3 or 5 floor.\nClues: P lives just above M and on the even\nnumbered floor. O lives above R’s floor but not\non the topmost floor. P doesn’t live on the\ntopmost floor.\nInference: So, case 1 would be rejected as P\ncannot be placed. So, Q must be living at\ntopmost floor.\nQ lives on topmost floor.\nQ29\nText Solution:\nStarting point: Here, we can start with T, S and N\nin order to form two cases.\nClues: S lives two floors above N, who lives on\nodd numbered floor. T lives on bottommost floor.\nInference: So, N lives on either 3 or 5 floor.\nClues: P lives just above M and on the even\nnumbered floor. O lives above R’s floor but not\non the topmost floor. P doesn’t live on the\ntopmost floor.\nInference: So, case 1 would be rejected as P\ncannot be placed. So, Q must be living at\ntopmost floor.\nT lives just below R’s floor.\n \nrd\nth\nrd\nth",
      "tables": [],
      "images": [
        "output\\images\\floor_puzzle_chapter_wise_dpp_english\\floor_puzzle_chapter_wise_dpp_english_p040_img01.png",
        "output\\images\\floor_puzzle_chapter_wise_dpp_english\\floor_puzzle_chapter_wise_dpp_english_p040_img02.png",
        "output\\images\\floor_puzzle_chapter_wise_dpp_english\\floor_puzzle_chapter_wise_dpp_english_p040_img03.png",
        "output\\images\\floor_puzzle_chapter_wise_dpp_english\\floor_puzzle_chapter_wise_dpp_english_p040_img04.png"
      ]
    }
  ]
}